{"data": [{"marker": {"color": ["#0072B2", "#D55E00", "#0072B2", "#D55E00", "#D55E00", "#0072B2", "#D55E00", "#0072B2", "#0072B2", "#0072B2", "#0072B2", "#D55E00", "#0072B2", "#D55E00", "#0072B2", "#0072B2", "#D55E00", "#0072B2", "#D55E00", "#0072B2", "#D55E00", "#D55E00", "#D55E00", "#D55E00", "#0072B2", "#D55E00", "#0072B2", "#D55E00", "#0072B2", "#D55E00", "#D55E00", "#0072B2", "#D55E00", "#0072B2", "#D55E00", "#0072B2", "#0072B2", "#D55E00", "#D55E00", "#D55E00", "#0072B2"]}, "name": "Cross-Correlation", "x": [-20, -19, -18, -17, -16, -15, -14, -13, -12, -11, -10, -9, -8, -7, -6, -5, -4, -3, -2, -1, 0, 1, 2, 3, 4, 5, 6, 7, 8, 9, 10, 11, 12, 13, 14, 15, 16, 17, 18, 19, 20], "y": [0.006061477734312088, -0.010353002149509048, 0.010091394326215638, -0.0017459680075351575, -0.007003474285606324, 0.01285128130648085, -0.021272734177699117, 0.007735595891247612, 0.009490772523094507, 0.005105848663223653, 0.011061804997518016, -0.02419592969632971, 0.025901759523645335, -0.03281871966579535, 0.011756782396124477, 0.006075965448186718, -0.0013185412447559767, 0.014590016182347227, -0.054580431426363964, 0.34190453019100997, -0.15452049972185142, -0.08562490660728982, -0.04302511458581859, -0.013111811897763288, 0.038266530643118836, -0.05578696821640999, 0.03748069259363932, -0.027990913527908935, 0.03393013416727587, -0.00574838180164441, -0.03174191086327902, 0.035429185894753336, -0.03480702977696715, 0.0015686829843426723, -0.016835026545232768, 0.0168121094492802, 0.048488451755917504, -0.038639145251824235, -0.0018388805475564977, -0.0017249183194332674, 0.023165779166240855], "type": "bar"}], "layout": {"template": {"data": {"barpolar": [{"marker": {"line": {"color": "white", "width": 0.5}, "pattern": {"fillmode": "overlay", "size": 10, "solidity": 0.2}}, "type": "barpolar"}], "bar": [{"error_x": {"color": "#2a3f5f"}, "error_y": {"color": "#2a3f5f"}, "marker": {"line": {"color": "white", "width": 0.5}, "pattern": {"fillmode": "overlay", "size": 10, "solidity": 0.2}}, "type": "bar"}], "carpet": [{"aaxis": {"endlinecolor": "#2a3f5f", "gridcolor": "#C8D4E3", "linecolor": "#C8D4E3", "minorgridcolor": "#C8D4E3", "startlinecolor": "#2a3f5f"}, "baxis": {"endlinecolor": "#2a3f5f", "gridcolor": "#C8D4E3", "linecolor": "#C8D4E3", "minorgridcolor": "#C8D4E3", "startlinecolor": "#2a3f5f"}, "type": "carpet"}], "choropleth": [{"colorbar": {"outlinewidth": 0, "ticks": ""}, "type": "choropleth"}], "contourcarpet": [{"colorbar": {"outlinewidth": 0, "ticks": ""}, "type": "contourcarpet"}], "contour": [{"colorbar": {"outlinewidth": 0, "ticks": ""}, "colorscale": [[0.0, "#0d0887"], [0.1111111111111111, "#46039f"], [0.2222222222222222, "#7201a8"], [0.3333333333333333, "#9c179e"], [0.4444444444444444, "#bd3786"], [0.5555555555555556, "#d8576b"], [0.6666666666666666, "#ed7953"], [0.7777777777777778, "#fb9f3a"], [0.8888888888888888, "#fdca26"], [1.0, "#f0f921"]], "type": "contour"}], "heatmap": [{"colorbar": {"outlinewidth": 0, "ticks": ""}, "colorscale": [[0.0, "#0d0887"], [0.1111111111111111, "#46039f"], [0.2222222222222222, "#7201a8"], [0.3333333333333333, "#9c179e"], [0.4444444444444444, "#bd3786"], [0.5555555555555556, "#d8576b"], [0.6666666666666666, "#ed7953"], [0.7777777777777778, "#fb9f3a"], [0.8888888888888888, "#fdca26"], [1.0, "#f0f921"]], "type": "heatmap"}], "histogram2dcontour": [{"colorbar": {"outlinewidth": 0, "ticks": ""}, "colorscale": [[0.0, "#0d0887"], [0.1111111111111111, "#46039f"], [0.2222222222222222, "#7201a8"], [0.3333333333333333, "#9c179e"], [0.4444444444444444, "#bd3786"], [0.5555555555555556, "#d8576b"], [0.6666666666666666, "#ed7953"], [0.7777777777777778, "#fb9f3a"], [0.8888888888888888, "#fdca26"], [1.0, "#f0f921"]], "type": "histogram2dcontour"}], "histogram2d": [{"colorbar": {"outlinewidth": 0, "ticks": ""}, "colorscale": [[0.0, "#0d0887"], [0.1111111111111111, "#46039f"], [0.2222222222222222, "#7201a8"], [0.3333333333333333, "#9c179e"], [0.4444444444444444, "#bd3786"], [0.5555555555555556, "#d8576b"], [0.6666666666666666, "#ed7953"], [0.7777777777777778, "#fb9f3a"], [0.8888888888888888, "#fdca26"], [1.0, "#f0f921"]], "type": "histogram2d"}], "histogram": [{"marker": {"pattern": {"fillmode": "overlay", "size": 10, "solidity": 0.2}}, "type": "histogram"}], "mesh3d": [{"colorbar": {"outlinewidth": 0, "ticks": ""}, "type": "mesh3d"}], "parcoords": [{"line": {"colorbar": {"outlinewidth": 0, "ticks": ""}}, "type": "parcoords"}], "pie": [{"automargin": true, "type": "pie"}], "scatter3d": [{"line": {"colorbar": {"outlinewidth": 0, "ticks": ""}}, "marker": {"colorbar": {"outlinewidth": 0, "ticks": ""}}, "type": "scatter3d"}], "scattercarpet": [{"marker": {"colorbar": {"outlinewidth": 0, "ticks": ""}}, "type": "scattercarpet"}], "scattergeo": [{"marker": {"colorbar": {"outlinewidth": 0, "ticks": ""}}, "type": "scattergeo"}], "scattergl": [{"marker": {"colorbar": {"outlinewidth": 0, "ticks": ""}}, "type": "scattergl"}], "scattermapbox": [{"marker": {"colorbar": {"outlinewidth": 0, "ticks": ""}}, "type": "scattermapbox"}], "scattermap": [{"marker": {"colorbar": {"outlinewidth": 0, "ticks": ""}}, "type": "scattermap"}], "scatterpolargl": [{"marker": {"colorbar": {"outlinewidth": 0, "ticks": ""}}, "type": "scatterpolargl"}], "scatterpolar": [{"marker": {"colorbar": {"outlinewidth": 0, "ticks": ""}}, "type": "scatterpolar"}], "scatter": [{"fillpattern": {"fillmode": "overlay", "size": 10, "solidity": 0.2}, "type": "scatter"}], "scatterternary": [{"marker": {"colorbar": {"outlinewidth": 0, "ticks": ""}}, "type": "scatterternary"}], "surface": [{"colorbar": {"outlinewidth": 0, "ticks": ""}, "colorscale": [[0.0, "#0d0887"], [0.1111111111111111, "#46039f"], [0.2222222222222222, "#7201a8"], [0.3333333333333333, "#9c179e"], [0.4444444444444444, "#bd3786"], [0.5555555555555556, "#d8576b"], [0.6666666666666666, "#ed7953"], [0.7777777777777778, "#fb9f3a"], [0.8888888888888888, "#fdca26"], [1.0, "#f0f921"]], "type": "surface"}], "table": [{"cells": {"fill": {"color": "#EBF0F8"}, "line": {"color": "white"}}, "header": {"fill": {"color": "#C8D4E3"}, "line": {"color": "white"}}, "type": "table"}]}, "layout": {"annotationdefaults": {"arrowcolor": "#2a3f5f", "arrowhead": 0, "arrowwidth": 1}, "autotypenumbers": "strict", "coloraxis": {"colorbar": {"outlinewidth": 0, "ticks": ""}}, "colorscale": {"diverging": [[0, "#8e0152"], [0.1, "#c51b7d"], [0.2, "#de77ae"], [0.3, "#f1b6da"], [0.4, "#fde0ef"], [0.5, "#f7f7f7"], [0.6, "#e6f5d0"], [0.7, "#b8e186"], [0.8, "#7fbc41"], [0.9, "#4d9221"], [1, "#276419"]], "sequential": [[0.0, "#0d0887"], [0.1111111111111111, "#46039f"], [0.2222222222222222, "#7201a8"], [0.3333333333333333, "#9c179e"], [0.4444444444444444, "#bd3786"], [0.5555555555555556, "#d8576b"], [0.6666666666666666, "#ed7953"], [0.7777777777777778, "#fb9f3a"], [0.8888888888888888, "#fdca26"], [1.0, "#f0f921"]], "sequentialminus": [[0.0, "#0d0887"], [0.1111111111111111, "#46039f"], [0.2222222222222222, "#7201a8"], [0.3333333333333333, "#9c179e"], [0.4444444444444444, "#bd3786"], [0.5555555555555556, "#d8576b"], [0.6666666666666666, "#ed7953"], [0.7777777777777778, "#fb9f3a"], [0.8888888888888888, "#fdca26"], [1.0, "#f0f921"]]}, "colorway": ["#636efa", "#EF553B", "#00cc96", "#ab63fa", "#FFA15A", "#19d3f3", "#FF6692", "#B6E880", "#FF97FF", "#FECB52"], "font": {"color": "#2a3f5f"}, "geo": {"bgcolor": "white", "lakecolor": "white", "landcolor": "white", "showlakes": true, "showland": true, "subunitcolor": "#C8D4E3"}, "hoverlabel": {"align": "left"}, "hovermode": "closest", "mapbox": {"style": "light"}, "paper_bgcolor": "white", "plot_bgcolor": "white", "polar": {"angularaxis": {"gridcolor": "#EBF0F8", "linecolor": "#EBF0F8", "ticks": ""}, "bgcolor": "white", "radialaxis": {"gridcolor": "#EBF0F8", "linecolor": "#EBF0F8", "ticks": ""}}, "scene": {"xaxis": {"backgroundcolor": "white", "gridcolor": "#DFE8F3", "gridwidth": 2, "linecolor": "#EBF0F8", "showbackground": true, "ticks": "", "zerolinecolor": "#EBF0F8"}, "yaxis": {"backgroundcolor": "white", "gridcolor": "#DFE8F3", "gridwidth": 2, "linecolor": "#EBF0F8", "showbackground": true, "ticks": "", "zerolinecolor": "#EBF0F8"}, "zaxis": {"backgroundcolor": "white", "gridcolor": "#DFE8F3", "gridwidth": 2, "linecolor": "#EBF0F8", "showbackground": true, "ticks": "", "zerolinecolor": "#EBF0F8"}}, "shapedefaults": {"line": {"color": "#2a3f5f"}}, "ternary": {"aaxis": {"gridcolor": "#DFE8F3", "linecolor": "#A2B1C6", "ticks": ""}, "baxis": {"gridcolor": "#DFE8F3", "linecolor": "#A2B1C6", "ticks": ""}, "bgcolor": "white", "caxis": {"gridcolor": "#DFE8F3", "linecolor": "#A2B1C6", "ticks": ""}}, "title": {"x": 0.05}, "xaxis": {"automargin": true, "gridcolor": "#EBF0F8", "linecolor": "#EBF0F8", "ticks": "", "title": {"standoff": 15}, "zerolinecolor": "#EBF0F8", "zerolinewidth": 2}, "yaxis": {"automargin": true, "gridcolor": "#EBF0F8", "linecolor": "#EBF0F8", "ticks": "", "title": {"standoff": 15}, "zerolinecolor": "#EBF0F8", "zerolinewidth": 2}}}, "shapes": [{"line": {"color": "#999999", "dash": "dash", "width": 1}, "type": "line", "x0": 0, "x1": 1, "xref": "x domain", "y0": 0.023662594516346006, "y1": 0.023662594516346006, "yref": "y"}, {"line": {"color": "#999999", "dash": "dash", "width": 1}, "type": "line", "x0": 0, "x1": 1, "xref": "x domain", "y0": -0.023662594516346006, "y1": -0.023662594516346006, "yref": "y"}, {"line": {"color": "black", "width": 0.5}, "type": "line", "x0": 0, "x1": 1, "xref": "x domain", "y0": 0, "y1": 0, "yref": "y"}], "annotations": [{"font": {"size": 9}, "showarrow": false, "text": "\u00b195% CI (0.024)", "x": 1, "xanchor": "right", "xref": "x domain", "y": 0.023662594516346006, "yanchor": "bottom", "yref": "y"}, {"font": {"color": "#888888", "size": 9}, "showarrow": false, "text": "Pre-whitened CCF (first-difference both series). Dashed lines = \u00b195% significance bands.", "x": 0, "xanchor": "left", "xref": "paper", "y": -0.12, "yref": "paper"}], "title": {"text": "Negative Contemporaneous Cross-Correlation: Spread Widening Hits SPY Same Day"}, "margin": {"b": 80}, "xaxis": {"title": {"text": "Lag (days, negative = spread leads SPY)"}}, "yaxis": {"title": {"text": "Cross-Correlation"}}, "height": 450, "showlegend": false}}